jasudh/__init__.py
jasudh/code1.py
jasudh/code2.py
jasudh/code3.py
jasudh/code4.py
jasudh/code5.py
deep_node-0.5.dist-info/METADATA
deep_node-0.5.dist-info/WHEEL
deep_node-0.5.dist-info/top_level.txt
deep_node-0.5.dist-info/RECORD
